odoo/addons/crm_lead_to_event_registration/README.rst
odoo/addons/crm_lead_to_event_registration/__init__.py
odoo/addons/crm_lead_to_event_registration/__manifest__.py
odoo/addons/crm_lead_to_event_registration/i18n/crm_lead_to_event_registration.pot
odoo/addons/crm_lead_to_event_registration/i18n/es.po
odoo/addons/crm_lead_to_event_registration/i18n/it.po
odoo/addons/crm_lead_to_event_registration/images/converting.png
odoo/addons/crm_lead_to_event_registration/images/linked.png
odoo/addons/crm_lead_to_event_registration/images/linking.png
odoo/addons/crm_lead_to_event_registration/images/not_linked.png
odoo/addons/crm_lead_to_event_registration/models/__init__.py
odoo/addons/crm_lead_to_event_registration/models/crm_lead.py
odoo/addons/crm_lead_to_event_registration/readme/CONFIGURE.rst
odoo/addons/crm_lead_to_event_registration/readme/CONTRIBUTORS.rst
odoo/addons/crm_lead_to_event_registration/readme/DESCRIPTION.rst
odoo/addons/crm_lead_to_event_registration/readme/ROADMAP.rst
odoo/addons/crm_lead_to_event_registration/readme/USAGE.rst
odoo/addons/crm_lead_to_event_registration/static/description/icon.png
odoo/addons/crm_lead_to_event_registration/static/description/index.html
odoo/addons/crm_lead_to_event_registration/tests/__init__.py
odoo/addons/crm_lead_to_event_registration/tests/test_crm_lead_to_event_registration.py
odoo/addons/crm_lead_to_event_registration/views/crm_lead_view.xml
odoo/addons/crm_lead_to_event_registration/wizard/__init__.py
odoo/addons/crm_lead_to_event_registration/wizard/crm_lead_event_pick.py
odoo/addons/crm_lead_to_event_registration/wizard/crm_lead_event_pick_view.xml
odoo/addons/crm_lead_to_event_registration/wizard/crm_lead_to_opportunity.py
odoo/addons/crm_lead_to_event_registration/wizard/crm_lead_to_opportunity_view.xml
odoo12_addon_crm_lead_to_event_registration-12.0.1.0.0.99.dev6.dist-info/METADATA
odoo12_addon_crm_lead_to_event_registration-12.0.1.0.0.99.dev6.dist-info/WHEEL
odoo12_addon_crm_lead_to_event_registration-12.0.1.0.0.99.dev6.dist-info/top_level.txt
odoo12_addon_crm_lead_to_event_registration-12.0.1.0.0.99.dev6.dist-info/RECORD
